{
  "waves": [
    {
      "spawnAt": 1600,
      "enemies": [
        { "speed": 1.2 },
        { "speed": 1.2 },
        { "speed": 1.5 }
      ]
    },
    {
      "spawnAt": 950,
      "enemies": [
        { "speed": 1.5 },
        { "speed": 1.8 },
        { "speed": 1.5 },
        { "speed": 1.5 }
      ]
    },
    {
      "spawnAt": 550,
      "enemies": [
        { "speed": 1.8 },
        { "speed": 1.8 },
        { "speed": 2.0 },
        { "speed": 1.8 },
        { "speed": 2.0 }, 
        { "speed": 1.8 }
      ]
    }
  ],
  "boss": {
    "retreatY": 150,
    "r": 60,
    "health": 25,
    "chargeSpeed": 8,
    "retreatSpeed": 2,
    "chargePause": 100
  }
}
